atomic_lines-0.1.1rc6.dist-info/METADATA
atomic_lines-0.1.1rc6.dist-info/WHEEL
atomic_lines-0.1.1rc6.dist-info/licenses/LICENSE
atomiclines/__init__.py
atomiclines/atomiclinereader.py
atomiclines/backgroundtask.py
atomiclines/exception.py
atomiclines/lineprocessor.py
atomiclines/log.py
atomiclines/processors.py
atomiclines/py.typed
atomic_lines-0.1.1rc6.dist-info/RECORD
