Metadata-Version: 2.1
Name: atomic-lines
Version: 0.1.1rc6
Summary: Helpers for asynchronous line processing. Some asynchronous readline implementations consume data if a readline() call times out. This is a wrapper for those implementations, guranteeing that either full lines are returned or nothing.
Keywords: readline async
Author-Email: Malte Vesper <malte.vesper@gmx.net>
License: MIT
Classifier: Development Status :: 4 - Beta
Classifier: Framework :: AsyncIO
Classifier: Programming Language :: Python :: 3
Classifier: Programming Language :: Python :: 3.11
Classifier: License :: OSI Approved :: MIT License
Classifier: Operating System :: OS Independent
Classifier: Typing :: Typed
Project-URL: Documentation, https://maltevesper.github.io/atomiclines/
Project-URL: Repository, https://github.com/maltevesper/atomiclines
Project-URL: Changelog, https://github.com/maltevesper/atomiclines/blob/main/CHANGELOG.md
Requires-Python: >=3.11
Requires-Dist: pyyaml>=6.0.1
Requires-Dist: more-itertools>=10.1.0
